Metadata-Version: 2.1
Name: polyfempy
Version: 0.2.3
Summary: Polyfem Python Bindings
Home-page: https://polyfem.github.io/
Author: Teseo Schneider
Author-email: 
License: UNKNOWN
Platform: UNKNOWN
Classifier: Programming Language :: Python :: 3
Classifier: License :: OSI Approved :: MIT License
